beamline_console/__init__.py
beamline_console/base_widget.py
beamline_console/beamline_console.desktop
beamline_console/beamline_console.sh
beamline_console/beamlinehal.py
beamline_console/constants.py
beamline_console/main_window.py
beamline_console/release.py
beamline_console/default_config/__init__.py
beamline_console/default_config/background.png
beamline_console/default_config/devices.xml
beamline_console/default_config/main.cfg
beamline_console/default_config/slots.xml
beamline_console/devicecontrol/__init__.py
beamline_console/devicecontrol/beamlinegraphicsscene.py
beamline_console/devicecontrol/beamlinewidget.py
beamline_console/devicecontrol/devicehistorydialog.py
beamline_console/devicecontrol/devicewidget.py
beamline_console/devicecontrol/motoritemwidget.py
beamline_console/devicecontrol/motorpropsdialog.py
beamline_console/devicecontrol/deviceitem/__init__.py
beamline_console/devicecontrol/deviceitem/devicegraphicsitem.py
beamline_console/devicecontrol/deviceitem/frameitem.py
beamline_console/devicecontrol/deviceitem/statusitem.py
beamline_console/devicecontrol/deviceitem/titleitem.py
beamline_console/devices/__init__.py
beamline_console/devices/abstractmotor.py
beamline_console/devices/dummymotor.py
beamline_console/devices/motordevice.py
beamline_console/devices/tangomotor.py
beamline_console/gui/AboutDialog_ui.py
beamline_console/gui/BeamlineWidget_ui.py
beamline_console/gui/DeviceItem_ui.py
beamline_console/gui/DeviceWidget_ui.py
beamline_console/gui/ErrorDialog_ui.py
beamline_console/gui/InputDialog_ui.py
beamline_console/gui/LoggingWidget_ui.py
beamline_console/gui/MainWindow_ui.py
beamline_console/gui/MotorItemWidget_ui.py
beamline_console/gui/MotorPropsDialog_ui.py
beamline_console/gui/SaveSnapshotDialog_ui.py
beamline_console/gui/SnapshotWidget_ui.py
beamline_console/gui/__init__.py
beamline_console/gui/icons_rc.py
beamline_console/logger/__init__.py
beamline_console/logger/guilogger.py
beamline_console/logger/highlightlogs.py
beamline_console-1.4.0.dist-info/LICENSE.txt
beamline_console-1.4.0.dist-info/METADATA
beamline_console-1.4.0.dist-info/WHEEL
beamline_console-1.4.0.dist-info/entry_points.txt
beamline_console-1.4.0.dist-info/top_level.txt
beamline_console-1.4.0.dist-info/RECORD
